sml/__init__.py
sml/auth.py
sml/baskerville.py
sml/casebook.py
sml/cli.py
sml/client.py
sml/config.py
sml/galleon.py
sml/hound.py
sml/parse.py
sml/shell.py
sml/update.py
sml/version.py
sml-0.10.3.dist-info/METADATA
sml-0.10.3.dist-info/RECORD
sml-0.10.3.dist-info/WHEEL
sml-0.10.3.dist-info/entry_points.txt
sml-0.10.3.dist-info/top_level.txt
test/__init__.py
test/test_config.py
test/test_parse.py
